<settings>

    <profiles>
        <profile>
            <id>install-dependencies</id>
            <repositories>
               <repository>
                    <id>Staging</id>
                    <name>Nexus Staging Mirror</name>
                    <url>https://oss.sonatype.org/content/groups/staging/</url>
                </repository>
                <repository>
                    <id>Releases</id>
                    <name>Nexus Releases</name>
                    <url>https://oss.sonatype.org/service/local/repositories/releases/content/</url>
                </repository>
                <repository>
                    <id>Central</id>
                    <name>Maven Central</name>
                    <url>http://repo.maven.apache.org/maven2</url>
                </repository>
           </repositories>
        </profile>
    </profiles>

    <activeProfiles>
        <activeProfile>install-dependencies</activeProfile>
    </activeProfiles>

</settings>